MANIFEST.in
README.rst
setup.py
rabbitmqStats/__init__.py
rabbitmqStats/_config.py
rabbitmqStats/main.py
rabbitmqStats/rabbitmqStats.py
rabbitmqStats.egg-info/PKG-INFO
rabbitmqStats.egg-info/SOURCES.txt
rabbitmqStats.egg-info/dependency_links.txt
rabbitmqStats.egg-info/entry_points.txt
rabbitmqStats.egg-info/requires.txt
rabbitmqStats.egg-info/top_level.txt