Metadata-Version: 1.1
Name: rabbitmqStats
Version: 0.1.2.post1
Summary: Gather RabbitMQ Stats for external logging
Home-page: https://github.com/CodeBleu/rabbitmqStats
Author: Jason Hollis
Author-email: jhollis@jdubb.net
License: MIT
Platform: UNKNOWN
Classifier: Development Status :: 3 - Alpha
Classifier: Environment :: Console
Classifier: Intended Audience :: Developers
Classifier: License :: OSI Approved :: MIT License
Classifier: Natural Language :: English
Classifier: Programming Language :: Python :: 2.6
Classifier: Programming Language :: Python :: 2.7
